langchain_huggy/__init__.py
langchain_huggy/core/__init__.py
langchain_huggy/core/_base_huggy_chat.py
langchain_huggy/core/_base_llm.py
langchain_huggy/core/_base_login.py
langchain_huggy/server/__init__.py
langchain_huggy/server/api.py
langchain_huggy/server/simple_streamlit_app.py
langchain_huggy/utils/__init__.py
langchain_huggy/utils/const.py
langchain_huggy-0.2.8.dist-info/LICENSE
langchain_huggy-0.2.8.dist-info/METADATA
langchain_huggy-0.2.8.dist-info/WHEEL
langchain_huggy-0.2.8.dist-info/top_level.txt
langchain_huggy-0.2.8.dist-info/RECORD
