Metadata-Version: 2.1
Name: langchain_huggy
Version: 0.2.8
Summary: A LangChain integration for HuggingChat models
Author-email: Kammari santhosh <your.email@example.com>
Project-URL: Homepage, https://github.com/yourusername/langchain_huggy
Project-URL: Bug Tracker, https://github.com/yourusername/langchain_huggy/issues
Classifier: Programming Language :: Python :: 3
Classifier: License :: OSI Approved :: MIT License
Classifier: Operating System :: OS Independent
Requires-Python: >=3.7
License-File: LICENSE
Requires-Dist: langchain-core
Requires-Dist: hugchat
Provides-Extra: dev
Requires-Dist: pytest ; extra == 'dev'
Requires-Dist: black ; extra == 'dev'
Requires-Dist: isort ; extra == 'dev'
